muclearn/__init__.py
muclearn/date.py
muclearn/mvg.py
muclearn/resources/ferien_by.json
muclearn-0.1.3.dist-info/LICENSE
muclearn-0.1.3.dist-info/WHEEL
muclearn-0.1.3.dist-info/METADATA
muclearn-0.1.3.dist-info/RECORD
