Metadata-Version: 2.1
Name: muclearn
Version: 0.1.3
Summary: A collection of helpers and tools for machine learning.
License: MIT
Author: Fabian Reinold
Author-email: fabian.reinold@muenchen.de
Requires-Python: >=3.8,<4.0
Classifier: License :: OSI Approved :: MIT License
Classifier: Programming Language :: Python :: 3
Classifier: Programming Language :: Python :: 3.10
Classifier: Programming Language :: Python :: 3.8
Classifier: Programming Language :: Python :: 3.9
Requires-Dist: geopy (>=2.3.0,<3.0.0)
Requires-Dist: holidays (>=0.14.2,<0.15.0)
Requires-Dist: pandas (>=1.5,<2.0)
Requires-Dist: requests (>=2,<3)
Requires-Dist: scikit-learn (>=1,<2)
